mcp_server_spira/__init__.py
mcp_server_spira/__main__.py
mcp_server_spira/server.py
mcp_server_spira/features/__init__.py
mcp_server_spira/features/common.py
mcp_server_spira/features/formatting.py
mcp_server_spira/features/automation/__init__.py
mcp_server_spira/features/automation/tools/__init__.py
mcp_server_spira/features/automation/tools/automatedtestruns.py
mcp_server_spira/features/automation/tools/builds.py
mcp_server_spira/features/mywork/__init__.py
mcp_server_spira/features/mywork/tools/__init__.py
mcp_server_spira/features/mywork/tools/myincidents.py
mcp_server_spira/features/mywork/tools/myrequirements.py
mcp_server_spira/features/mywork/tools/mytasks.py
mcp_server_spira/features/mywork/tools/mytestcases.py
mcp_server_spira/features/mywork/tools/mytestsets.py
mcp_server_spira/features/productartifacts/__init__.py
mcp_server_spira/features/productartifacts/tools/__init__.py
mcp_server_spira/features/productartifacts/tools/automationhosts.py
mcp_server_spira/features/productartifacts/tools/incidents.py
mcp_server_spira/features/productartifacts/tools/releases.py
mcp_server_spira/features/productartifacts/tools/requirements.py
mcp_server_spira/features/productartifacts/tools/risks.py
mcp_server_spira/features/productartifacts/tools/tasks.py
mcp_server_spira/features/productartifacts/tools/testcases.py
mcp_server_spira/features/productartifacts/tools/testruns.py
mcp_server_spira/features/productartifacts/tools/testsets.py
mcp_server_spira/features/programartifacts/__init__.py
mcp_server_spira/features/programartifacts/tools/__init__.py
mcp_server_spira/features/programartifacts/tools/capabilities.py
mcp_server_spira/features/programartifacts/tools/milestones.py
mcp_server_spira/features/specifications/__init__.py
mcp_server_spira/features/specifications/tools/__init__.py
mcp_server_spira/features/specifications/tools/productspecification.py
mcp_server_spira/features/templateconfiguration/__init__.py
mcp_server_spira-1.1.1.dist-info/licenses/LICENSE
mcp_server_spira-1.1.1.dist-info/METADATA
mcp_server_spira-1.1.1.dist-info/WHEEL
mcp_server_spira-1.1.1.dist-info/top_level.txt
mcp_server_spira-1.1.1.dist-info/RECORD
