Metadata-Version: 2.4
Name: mcp-server-spira
Version: 1.1.1
Summary: A Model Context Protocol (MCP) server enabling AI assistants to interact with Spira by Inflectra.
Home-page: https://github.com/Inflectra/mcp-server-spira
Author: Inflectra Corporation
Author-email: support@inflectra.com
License-Expression: MIT
Project-URL: Homepage, https://github.com/Inflectra/mcp-server-spira
Project-URL: Documentation, https://www.inflectra.com/Ideas/Entry/using-the-spira-mcp-server-in-vs-code-part-1-1902.aspx
Project-URL: Repository, https://github.com/Inflectra/mcp-server-spira.git
Keywords: MCP,AI,GenAI
Classifier: Topic :: Scientific/Engineering :: Artificial Intelligence
Classifier: Programming Language :: Python :: 3
Classifier: Operating System :: OS Independent
Requires-Python: >=3.12
License-File: LICENSE
Requires-Dist: httpx>=0.28.1
Requires-Dist: mcp[cli]>=1.9.2
Requires-Dist: pytest>=8.4.0
Dynamic: author
Dynamic: author-email
Dynamic: home-page
Dynamic: license-file
